Metadata-Version: 2.1
Name: pyaw
Version: 0.0.2
Summary: Python Assembly Wrapper
Home-page: https://github.com/ninjamar/pyaw
Author: ninjamar
License: UNKNOWN
Platform: UNKNOWN
Requires-Python: >=3.7
License-File: LICENSE
